repoze
tests
test_elixir
