Metadata-Version: 1.0
Name: repoze.what.plugins.sql
Version: 1.0rc4
Summary: The repoze.what SQL plugin
Home-page: http://code.gustavonarea.net/repoze.what.plugins.sql/
Author: Gustavo Narea
Author-email: repoze-dev@lists.repoze.org
License: BSD-derived (http://www.repoze.org/LICENSE.txt)
Keywords: web application wsgi server wsgi sql sqlalchemy elixir authorization repoze
Platform: UNKNOWN
Classifier: Development Status :: 4 - Beta
Classifier: Environment :: Web Environment
Classifier: Intended Audience :: Developers
Classifier: Natural Language :: English
Classifier: Operating System :: OS Independent
Classifier: Programming Language :: Python
Classifier: Topic :: Database
Classifier: Topic :: Internet :: WWW/HTTP :: WSGI
Classifier: Topic :: Security
